3_Sequential/FSM/Sequence_detector/Moore_FSM/1001_FSM/1001_overlapping.v
module moore_fsm(
input clk,rst,a,
output reg q);
parameter [2:0] s0=3'b000,
            s1=3'b001,
            s2=3'b010,
            s3=3'b011,
            s4=3'b100;
reg [2:0]state,next_state;
always@(posedge clk or posedge rst)begin
state<=2'b00; 
q<=1'b0;
if(rst)
state<=2'b00;
else
state<=next_state;
end
always@(*) begin
case(state)
s0:begin	
if(a)
next_state<=s1;
else
next_state<=s0;
end
s1:begin
if(a)
next_state<=s1;
else
next_state<=s2;
end
s2:begin
if(a)
next_state<=s1;
else	
next_state<=s3;
end
s3:begin
if(a) 
next_state<=s4;
else 
next_state<=s0;
end
s4:begin
q<=1'b1;	
if(a)
next_state<=s1;
else
next_state<=s2;
end
endcase
end
endmodule

3_Sequential/FSM/Sequence_detector/Moore_FSM/1001_FSM/tb_1001_overlapping.v
module tb_moore_fsm;
reg clk,rst,a;
wire q;
moore_fsm uut(.clk(clk), .rst(rst), .a(a), .q(q));
always #5 clk=~clk;
initial begin
	clk=0; rst=1; a=0;
	#5 rst=0;
	#10 a=1;
	#10 a=1;
	#10 a=0;
	#10 a=0;
	#10 a=1;
	#10 a=0;
	#10 a=0;
	#10 a=1;
        #10 a=1;
	#10 $finish;
end
initial begin
	$monitor("Time=%0t | clk=%b | rst=%b | a=%b | q=%b",$time,clk,rst,a,q);
	$dumpfile("over_moore_fsm");
	$dumpvars(0,tb_moore_fsm);
end
endmodule

3_Sequential/FSM/Sequence_detector/Moore_FSM/1001_FSM/nonover_moore_fsm.vcd
$date
	Mon Mar  2 11:07:37 2026
$end
$version
	Icarus Verilog
$end
$timescale
	1s
$end
$scope module tb_moore_fsm $end
$var wire 1 ! q $end
$var reg 1 " a $end
$var reg 1 # clk $end
$var reg 1 $ rst $end
$scope module uut $end
$var wire 1 " a $end
$var wire 1 # clk $end
$var wire 1 $ rst $end
$var parameter 3 % s0 $end
$var parameter 3 & s1 $end
$var parameter 3 ' s2 $end
$var parameter 3 ( s3 $end
$var parameter 3 ) s4 $end
$var reg 3 * next_state [2:0] $end
$var reg 1 ! q $end
$var reg 3 + state [2:0] $end
$upscope $end
$upscope $end
$enddefinitions $end
$comment Show the parameter values. $end
$dumpall
b100 )
b11 (
b10 '
b1 &
b0 %
$end
#0
$dumpvars
b0 +
b0 *
1$
0#
0"
0!
$end
#5
0$
1#
#10
0#
#15
b1 *
1#
1"
#20
0#
#25
b1 +
1#
#30
0#
#35
b1 +
b10 *
1#
0"
#40
0#
#45
b11 *
b10 +
1#
#50
0#
#55
b11 +
b100 *
1#
1"
#60
0#
#65
b1 *
1!
b100 +
1#
#70
0#
#75
0!
b1 +
b10 *
1#
0"
#80
0#
#85
b11 *
b10 +
1#
#90
0#
#95
b11 +
b100 *
1#
1"
#100
0#
#105
b1 *
1!
b100 +
1#
#110
0#
#115
0!
b1 +
1#
