2_Combinational/Adders/Full_adder_Structure.v
module full_adder(
input a,b,cin,
output sum,carry);
wire x,y,z;
xor x1(x,a,b);
and a1(y,x,cin);
and a2(z,a,b);
xor x2(sum,x,cin);
or o1(carry,y,z);
endmodule

2_Combinational/Adders/tb_Full_adder.v
module tb_Full_adder;
reg a,b,cin;
wire sum,carry;
full_adder f1(.a(a), .b(b), .cin(cin), .sum(sum), .carry(carry));
initial begin
a=0; b=0; cin=0;
#10 a=0; b=0; cin=1;
#10 a=0; b=1; cin=0;
#10 a=0; b=1; cin=1;
#10 a=1; b=0; cin=0;
#10 a=1; b=0; cin=1;
#10 a=1; b=1; cin=0;
#10 a=1; b=1; cin=1;
#10 $finish;
end
initial begin
$monitor("Time=%0t | a=%0b | b=%0b | c=%0b |  sum=%0b | carry=%0b",$time,a,b,cin,sum,carry);
$dumpfile("tb_full_adder.vcd");
$dumpvars(0,tb_Full_adder);
end
endmodule

2_Combinational/Adders/tb_full_adder.vcd
$date
	Wed Feb  4 12:49:53 2026
$end
$version
	Icarus Verilog
$end
$timescale
	1s
$end
$scope module tb_Full_adder $end
$var wire 1 ! sum $end
$var wire 1 " carry $end
$var reg 1 # a $end
$var reg 1 $ b $end
$var reg 1 % cin $end
$scope module f1 $end
$var wire 1 # a $end
$var wire 1 $ b $end
$var wire 1 " carry $end
$var wire 1 % cin $end
$var wire 1 & z $end
$var wire 1 ' y $end
$var wire 1 ( x $end
$var wire 1 ! sum $end
$scope module h1 $end
$var wire 1 # a $end
$var wire 1 $ b $end
$var wire 1 ' carry $end
$var wire 1 ( sum $end
$upscope $end
$scope module h2 $end
$var wire 1 ( a $end
$var wire 1 % b $end
$var wire 1 & carry $end
$var wire 1 ! sum $end
$upscope $end
$upscope $end
$upscope $end
$enddefinitions $end
$comment Show the parameter values. $end
$dumpall
$end
#0
$dumpvars
0(
0'
0&
0%
0$
0#
0"
0!
$end
#10
1!
1%
#20
1(
0%
1$
#30
1"
0!
1&
1%
#40
0"
1!
0&
0%
0$
1#
#50
1"
0!
1&
1%
#60
0&
0(
1'
0%
1$
#70
1!
1%
