2_Combinational/Adders/ripple_adder_using_generate.v
module full_adder(
input a,b,cin,
output sum,carry);
assign sum=a^b^cin;
assign carry=((a^b)&cin|a&b);
endmodule

module ripple_carry_adder #(parameter N=4)
(input [N-1:0]a,b,
	input cin,
	output [N-1:0]sum,
	output cout);
wire [N:0]c;
assign c[0]=cin;
genvar i;
generate
for(i=0;i<N;i=i+1)begin
full_adder fa(.a(a[i]), .b(b[i]), .cin(c[i]), .sum(sum[i]), .carry(c[i+1]));
end
endgenerate
assign cout=c[N];
endmodule

2_Combinational/Adders/tb_ripple_adder.v
module tb_ripple_adder;
reg [3:0]a,b;
reg cin;
wire [3:0]sum;
wire cout;
ripple_carry_adder dut(.a(a), .b(b), .cin(cin), .sum(sum), .cout(cout));
initial begin
a=4'b0000; b=4'b0000; cin=0;
#10 a=4'b0001; b=4'b0000; cin=0;
 #10 a=4'b0010; b=4'b1000; cin=0; 
 #10 a=4'b1000; b=4'b0011; cin=1; 
 #10 a=4'b1001; b=4'b0001; cin=0; 
 #10 a=4'b0100; b=4'b0110; cin=0; 
 #10 a=4'b0101; b=4'b0111; cin=1; 
 #10 a=4'b1001; b=4'b0010; cin=0; 
 #10 a=4'b0001; b=4'b0101; cin=0; 
 #20 $finish;
 end
 initial begin
$monitor("Time=%0t | a=%b | b=%b | cin=%b | sum=%b | cout=%b",$time,a,b,cin,sum,cout);
$dumpfile("tb_ripple_adder.vcd");
$dumpvars(0,tb_ripple_adder);
end
endmodule

2_Combinational/Adders/tb_ripple_adder.vcd
$date
	Thu Feb  5 11:22:20 2026
$end
$version
	Icarus Verilog
$end
$timescale
	1s
$end
$scope module tb_ripple_adder $end
$var wire 4 ! sum [3:0] $end
$var wire 1 " cout $end
$var reg 4 # a [3:0] $end
$var reg 4 $ b [3:0] $end
$var reg 1 % cin $end
$scope module dut $end
$var wire 4 & a [3:0] $end
$var wire 4 ' b [3:0] $end
$var wire 1 % cin $end
$var wire 4 ( sum [3:0] $end
$var wire 1 " cout $end
$var wire 5 ) c [4:0] $end
$var parameter 32 * N $end
$scope begin genblk1[0] $end
$var parameter 2 + i $end
$scope module fa $end
$var wire 1 , a $end
$var wire 1 - b $end
$var wire 1 . carry $end
$var wire 1 / cin $end
$var wire 1 0 sum $end
$upscope $end
$upscope $end
$scope begin genblk1[1] $end
$var parameter 2 1 i $end
$scope module fa $end
$var wire 1 2 a $end
$var wire 1 3 b $end
$var wire 1 4 carry $end
$var wire 1 5 cin $end
$var wire 1 6 sum $end
$upscope $end
$upscope $end
$scope begin genblk1[2] $end
$var parameter 3 7 i $end
$scope module fa $end
$var wire 1 8 a $end
$var wire 1 9 b $end
$var wire 1 : carry $end
$var wire 1 ; cin $end
$var wire 1 < sum $end
$upscope $end
$upscope $end
$scope begin genblk1[3] $end
$var parameter 3 = i $end
$scope module fa $end
$var wire 1 > a $end
$var wire 1 ? b $end
$var wire 1 @ carry $end
$var wire 1 A cin $end
$var wire 1 B sum $end
$upscope $end
$upscope $end
$upscope $end
$upscope $end
$enddefinitions $end
$comment Show the parameter values. $end
$dumpall
b11 =
b10 7
b1 1
b0 +
b100 *
$end
#0
$dumpvars
0B
0A
0@
0?
0>
0<
0;
0:
09
08
06
05
04
03
02
00
0/
0.
0-
0,
b0 )
b0 (
b0 '
b0 &
0%
b0 $
b0 #
0"
b0 !
$end
#10
b1 !
b1 (
10
1,
b1 #
b1 &
#20
1B
00
b1010 !
b1010 (
16
1?
0,
12
b1000 $
b1000 '
b10 #
b10 &
#30
1<
1;
14
b1100 !
b1100 (
06
15
1.
1/
1-
13
0?
02
1>
b111 )
1%
b11 $
b11 '
b1000 #
b1000 &
#40
0<
0;
04
b1010 !
b1010 (
16
0/
03
1,
b10 )
0%
b1 $
b1 '
b1001 #
b1001 &
#50
0<
0;
04
05
1A
16
0.
b1000 )
1:
b1010 !
b1010 (
1B
0-
13
19
0,
18
0>
b110 $
b110 '
b100 #
b100 &
#60
1<
1;
14
06
15
1.
b1101 !
b1101 (
10
1/
1-
1,
b1111 )
1%
b111 $
b111 '
b101 #
b101 &
#70
0<
0;
04
16
0"
05
0A
0@
0.
0:
b1011 !
b1011 (
1B
0/
0-
09
08
1>
b0 )
0%
b10 $
b10 '
b1001 #
b1001 &
#80
15
00
b10 )
1.
16
1<
b110 !
b110 (
0B
1-
03
19
0>
b101 $
b101 '
b1 #
b1 &
