3_Sequential/Flip_Flops/T_flip_flop/async_t_ff.v
module t_ff(
input clk,rst,t,
output reg q,
output q_bar);
always@(posedge clk or posedge rst)begin
if(rst)
q<=1'b0;
else if(t)
q<=~q;
else
q<=q;
end
assign q_bar=~q;
endmodule

3_Sequential/Flip_Flops/T_flip_flop/tb_t_ff.v
module tb_t_ff;
reg clk,rst,t;
wire q,q_bar;
t_ff uut(.clk(clk), .rst(rst), .t(t), .q(q), .q_bar(q_bar));
always#5 clk=~clk;
initial begin
clk=0; rst=1; t=1;
#10 rst=0; t=1;
#10 t=0;
#10 t=1;
#10 rst=1; t=1;
#10 rst=0;
#10 $finish;
end
initial begin
$monitor("Time=%0t | clk=%b | rst=%b | t=%b | q=%b | q_bar=%b",$time,clk,rst,t,q,q_bar);
$dumpfile("tb_t_ff.vcd");
$dumpvars(0,tb_t_ff);
end
endmodule

3_Sequential/Flip_Flops/T_flip_flop/tb_t_ff.vcd
$date
	Wed Feb 11 16:40:21 2026
$end
$version
	Icarus Verilog
$end
$timescale
	1s
$end
$scope module tb_t_ff $end
$var wire 1 ! q_bar $end
$var wire 1 " q $end
$var reg 1 # clk $end
$var reg 1 $ rst $end
$var reg 1 % t $end
$scope module uut $end
$var wire 1 # clk $end
$var wire 1 ! q_bar $end
$var wire 1 $ rst $end
$var wire 1 % t $end
$var reg 1 " q $end
$upscope $end
$upscope $end
$enddefinitions $end
$comment Show the parameter values. $end
$dumpall
$end
#0
$dumpvars
1%
1$
0#
0"
1!
$end
#5
1#
#10
0#
0$
#15
0!
1"
1#
#20
0#
0%
#25
1#
#30
0#
1%
#35
1!
0"
1#
#40
0#
1$
#45
1#
#50
0#
0$
#55
0!
1"
1#
