3_Sequential/Flip_Flops/T_flip_flop/t_using_sr.v

module sr_ff(
input s,r,clk,rst,
output reg q,
output q_bar);
always @(posedge clk or posedge rst)
begin 
if(rst)
q<=1'b0;
else
case({s,r})
2'b00:q<=q;
2'b01:q<=1'b0;
2'b10:q<=1'b1;
2'b11:q<=1'bx;
endcase
end
assign q_bar=~q;
endmodule

module t_ff(
input t,clk,rst,
output q,q_bar);
assign d0= t&~q;
assign d1= t&q;
sr_ff sr1(
.s(d0),
.r(d1),
.clk(clk),
.rst(rst),
.q(q), .q_bar(q_bar));
endmodule

3_Sequential/Flip_Flops/T_flip_flop/tb_t_ff.v
module tb_t_ff;
reg clk,rst,t;
wire q,q_bar;
t_ff uut(.clk(clk), .rst(rst), .t(t), .q(q), .q_bar(q_bar));
always#5 clk=~clk;
initial begin
clk=0; rst=1; t=1;
#10 rst=0; t=1;
#10 t=0;
#10 t=1;
#10 rst=1; t=1;
#10 rst=0;
#10 $finish;
end
initial begin
$monitor("Time=%0t | clk=%b | rst=%b | t=%b | q=%b | q_bar=%b",$time,clk,rst,t,q,q_bar);
$dumpfile("tb_t_ff.vcd");
$dumpvars(0,tb_t_ff);
end
endmodule

3_Sequential/Flip_Flops/T_flip_flop/tb_t_ff.vcd
$date
	Tue Feb 17 10:38:46 2026
$end
$version
	Icarus Verilog
$end
$timescale
	1s
$end
$scope module tb_t_ff $end
$var wire 1 ! q_bar $end
$var wire 1 " q $end
$var reg 1 # clk $end
$var reg 1 $ rst $end
$var reg 1 % t $end
$scope module uut $end
$var wire 1 # clk $end
$var wire 1 & d0 $end
$var wire 1 ' d1 $end
$var wire 1 $ rst $end
$var wire 1 % t $end
$var wire 1 ! q_bar $end
$var wire 1 " q $end
$scope module sr1 $end
$var wire 1 # clk $end
$var wire 1 ! q_bar $end
$var wire 1 ' r $end
$var wire 1 $ rst $end
$var wire 1 & s $end
$var reg 1 " q $end
$upscope $end
$upscope $end
$upscope $end
$enddefinitions $end
$comment Show the parameter values. $end
$dumpall
$end
#0
$dumpvars
0'
1&
1%
1$
0#
0"
1!
$end
#5
1#
#10
0#
0$
#15
0&
0!
1'
1"
1#
#20
0'
0#
0%
#25
1#
#30
1'
0#
1%
#35
1&
1!
0'
0"
1#
#40
0#
1$
#45
1#
#50
0#
0$
#55
0&
0!
1'
1"
1#
