Clk_Divider/Clk_Divider_by_6/clk_divider_by_6_50%.v
module clk_divider_by_6(
input clk,rst,
output reg f_by_6);
reg [1:0] count;
always@(posedge clk or posedge rst) begin
if(rst) begin
f_by_6<=1'b0;
count<=2'b00;
end
else begin
  count<=count+1;
  if(count==2'b10) begin
      f_by_6<=~f_by_6;
      count<=2'b0;
  end
     	
end
end
endmodule

Clk_Divider/Clk_Divider_by_6/tb_clk_divider_by_6_25%.v
module tb_clk_divider_by_6;
reg clk,rst;
wire f_by_6;
clk_divider_by_6 uut(.clk(clk), .rst(rst), .f_by_6(f_by_6));
always #5 clk=~clk;
initial begin
clk=0; rst=1;
#5 rst=0;
#150 $finish;
end
initial begin
$monitor("Time=%0t | clk=%b | rst=%b | f_by_6=%b",$time,clk,rst,f_by_6);
$dumpfile("clk_divider_by_6_25%.vcd");
$dumpvars(0,tb_clk_divider_by_6);
end
endmodule

Clk_Divider/Clk_Divider_by_6/clk_divider_by_6_50%.vcd
$date
	Tue Mar  3 10:20:44 2026
$end
$version
	Icarus Verilog
$end
$timescale
	1s
$end
$scope module tb_clk_divider_by_6 $end
$var wire 1 ! f_by_6 $end
$var reg 1 " clk $end
$var reg 1 # rst $end
$scope module uut $end
$var wire 1 " clk $end
$var wire 1 # rst $end
$var reg 2 $ count [1:0] $end
$var reg 1 ! f_by_6 $end
$upscope $end
$upscope $end
$enddefinitions $end
$comment Show the parameter values. $end
$dumpall
$end
#0
$dumpvars
b0 $
1#
0"
0!
$end
#5
b1 $
0#
1"
#10
0"
#15
b10 $
1"
#20
0"
#25
1!
b0 $
1"
#30
0"
#35
b1 $
1"
#40
0"
#45
b10 $
1"
#50
0"
#55
0!
b0 $
1"
#60
0"
#65
b1 $
1"
#70
0"
#75
b10 $
1"
#80
0"
#85
1!
b0 $
1"
#90
0"
#95
b1 $
1"
#100
0"
#105
b10 $
1"
