Clk_Divider/Clk_Divider_by_6/clk_divider_by_6_75%.v
module clk_divider_by_6(
input clk,rst,
output f_by_6);
reg [2:0] count;
reg r_pos;
reg r_neg;
always@(posedge clk or posedge rst) begin
	if(rst)
		count<=3'b000;
	else
		count<=count+1;
end

always@(posedge clk or posedge rst) begin
	if(rst)
		r_pos<=1'b0;
		
        else begin
        if (count<=3'b011) 
                  r_pos<=1'b1;
         else if(count==3'b100) begin        
                  r_pos<=1'b0;
                  count<=3'b111;
                  end
                
end
end

always@(negedge clk or posedge rst) begin
	if(rst)
		r_neg<=1'b0;
	else
		r_neg<=r_pos;
end

assign f_by_6= r_pos | r_neg;
endmodule

Clk_Divider/Clk_Divider_by_6/tb_clk_divider_by_6_25%.v
module tb_clk_divider_by_6;
reg clk,rst;
wire f_by_6;
clk_divider_by_6 uut(.clk(clk), .rst(rst), .f_by_6(f_by_6));
always #5 clk=~clk;
initial begin
clk=0; rst=1;
#5 rst=0;
#150 $finish;
end
initial begin
$monitor("Time=%0t | clk=%b | rst=%b | f_by_6=%b",$time,clk,rst,f_by_6);
$dumpfile("clk_divider_by_6_25%.vcd");
$dumpvars(0,tb_clk_divider_by_6);
end
endmodule

Clk_Divider/Clk_Divider_by_6/clk_divider_by_6_25%.vcd
$date
	Tue Mar  3 11:02:12 2026
$end
$version
	Icarus Verilog
$end
$timescale
	1s
$end
$scope module tb_clk_divider_by_6 $end
$var wire 1 ! f_by_6 $end
$var reg 1 " clk $end
$var reg 1 # rst $end
$scope module uut $end
$var wire 1 " clk $end
$var wire 1 ! f_by_6 $end
$var wire 1 # rst $end
$var reg 3 $ count [2:0] $end
$var reg 1 % r_neg $end
$var reg 1 & r_pos $end
$upscope $end
$upscope $end
$enddefinitions $end
$comment Show the parameter values. $end
$dumpall
$end
#0
$dumpvars
0&
0%
b0 $
1#
0"
0!
$end
#5
1!
1&
b1 $
0#
1"
#10
1%
0"
#15
b10 $
0&
1"
#20
0!
0%
0"
#25
b11 $
1"
#30
0"
#35
b100 $
1"
#40
0"
#45
b101 $
1"
#50
0"
#55
b110 $
1"
#60
0"
#65
1!
1&
b1 $
1"
#70
1%
0"
#75
b10 $
0&
1"
#80
0!
0%
0"
#85
b11 $
1"
#90
0"
#95
b100 $
1"
#100
0"
#105
b101 $
1"
#110
0"
#115
b110 $
1"
#120
0"
#125
1!
1&
b1 $
1"
#130
1%
0"
#135
b10 $
0&
1"
#140
0!
0%
0"
#145
b11 $
1"
#150
0"
#155
b100 $
1"
