3_Sequential/Counters/Async_Counters/async_4bit_down_counter.v
module async_down_counter(
input clk,rst,
output [3:0]count);
reg [3:0]q;
wire [3:0]q_bar;

always@(posedge clk or posedge rst)begin
if(rst)
q<=4'b0000;
else
q[0]<=q[0]+1;
end

always@(posedge q[0] or posedge rst)begin
if(rst)
q<=4'b0000;
else
q[1]<=q[1]+1;
end

always@(posedge q[1] or posedge rst)begin
if(rst)
q<=4'b0000;
else
q[2]<=q[2]+1;
end

always@(posedge q[2] or posedge rst)begin
if(rst)
q<=4'b0000;
else
q[3]<=q[3]+1;
end
assign count=q;
assign q_bar=~q;
endmodule

3_Sequential/Counters/Async_Counters/tb_async_4bit_down_counter.v
module tb_async_down_counter;
reg clk,rst;
wire [3:0]count;
async_down_counter uut(.clk(clk), .rst(rst), .count(count));
always #5clk=~clk;
initial begin
clk=0; rst=0;
#10 rst=1;
#5 rst=0;
#50 rst=1;
#5 rst=0;
#100 $finish;
end
initial begin
$monitor("Time=%0t | clk=%b | rst=%b | count=%b",$time,clk,rst,count);
$dumpfile("async_4bit_down_counter.vcd");
$dumpvars(0,tb_async_down_counter);
end
endmodule

3_Sequential/Counters/Async_Counters/async_4bit_down_counter.vcd
$date
	Fri Feb 13 20:51:46 2026
$end
$version
	Icarus Verilog
$end
$timescale
	1s
$end
$scope module tb_async_down_counter $end
$var wire 4 ! count [3:0] $end
$var reg 1 " clk $end
$var reg 1 # rst $end
$scope module uut $end
$var wire 1 " clk $end
$var wire 4 $ count [3:0] $end
$var wire 4 % q_bar [3:0] $end
$var wire 1 # rst $end
$var reg 4 & q [3:0] $end
$upscope $end
$upscope $end
$enddefinitions $end
$comment Show the parameter values. $end
$dumpall
$end
#0
$dumpvars
bx &
bx %
bx $
0#
0"
bx !
$end
#5
1"
#10
b1111 %
b0 !
b0 $
b0 &
0"
1#
#15
b0 %
b1111 !
b1111 $
b1111 &
1"
0#
#20
0"
#25
b1 %
b1110 !
b1110 $
b1110 &
1"
#30
0"
#35
b10 %
b1101 !
b1101 $
b1101 &
1"
#40
0"
#45
b11 %
b1100 !
b1100 $
b1100 &
1"
#50
0"
#55
b100 %
b1011 !
b1011 $
b1011 &
1"
#60
0"
#65
b1111 %
b0 !
b0 $
b0 &
1"
1#
#70
0"
0#
#75
b0 %
b1111 !
b1111 $
b1111 &
1"
#80
0"
#85
b1 %
b1110 !
b1110 $
b1110 &
1"
#90
0"
#95
b10 %
b1101 !
b1101 $
b1101 &
1"
#100
0"
#105
b11 %
b1100 !
b1100 $
b1100 &
1"
#110
0"
#115
b100 %
b1011 !
b1011 $
b1011 &
1"
#120
0"
#125
b101 %
b1010 !
b1010 $
b1010 &
1"
#130
0"
#135
b110 %
b1001 !
b1001 $
b1001 &
1"
#140
0"
#145
b111 %
b1000 !
b1000 $
b1000 &
1"
#150
0"
#155
b1000 %
b111 !
b111 $
b111 &
1"
#160
0"
#165
b1001 %
b110 !
b110 $
b110 &
1"
