3_Sequential/Counters/Sync_Counters/sync_4bit_down_counter.v
module down_counter(
input clk,rst,
output reg[3:0]count);
always@(posedge clk)begin
if (rst)
count<=4'b0000;
else
count<=count-1;
end
endmodule

3_Sequential/Counters/Sync_Counters/tb_4bit_down_counter.v
module tb_down_counter;
reg clk,rst;
wire [3:0]count;
down_counter u1(.clk(clk), .rst(rst), .count(count));
always #5clk=~clk;
initial begin
clk=1; rst=1;
#10 rst=0;
#140 $finish;
end
initial begin
$monitor("Time=%0t | clk=%b | rst=%b | count=%b",$time,clk,rst,count);
$dumpfile("down_counter.vcd");
$dumpvars(0,tb_down_counter);
end
endmodule

3_Sequential/Counters/Sync_Counters/down_counter.vcd
$date
	Thu Feb 12 16:32:20 2026
$end
$version
	Icarus Verilog
$end
$timescale
	1s
$end
$scope module tb_down_counter $end
$var wire 4 ! count [3:0] $end
$var reg 1 " clk $end
$var reg 1 # rst $end
$scope module u1 $end
$var wire 1 " clk $end
$var wire 1 # rst $end
$var reg 4 $ count [3:0] $end
$upscope $end
$upscope $end
$enddefinitions $end
$comment Show the parameter values. $end
$dumpall
$end
#0
$dumpvars
b0 $
1#
1"
b0 !
$end
#5
0"
#10
b1111 !
b1111 $
1"
0#
#15
0"
#20
b1110 !
b1110 $
1"
#25
0"
#30
b1101 !
b1101 $
1"
#35
0"
#40
b1100 !
b1100 $
1"
#45
0"
#50
b1011 !
b1011 $
1"
#55
0"
#60
b1010 !
b1010 $
1"
#65
0"
#70
b1001 !
b1001 $
1"
#75
0"
#80
b1000 !
b1000 $
1"
#85
0"
#90
b111 !
b111 $
1"
#95
0"
#100
b110 !
b110 $
1"
#105
0"
#110
b101 !
b101 $
1"
#115
0"
#120
b100 !
b100 $
1"
#125
0"
#130
b11 !
b11 $
1"
#135
0"
#140
b10 !
b10 $
1"
#145
0"
#150
b1 !
b1 $
1"
