Assignments/Task&Functions/q24_function_prime.v
module prime_no 
#(parameter N=8)
(input [N-1:0]a,
output out);

function prime;
input [N-1:0]n;
integer i;
begin
if(n<=1)
prime=0;
else begin
prime=1;
for(i=2;i<n;i=i+1)begin
if(n%i==0)
prime=0;
end
end
end
endfunction

assign out=prime(a);
endmodule

Assignments/Task&Functions/tb_q24_function_prime.v
module tb_function_prime;
parameter N=8;
reg [N-1:0]a;
wire out;
prime_no #(.N(N)) uut(.a(a), .out(out));
integer i;
initial begin
for(i=0;i<12;i=i+1) begin
a=$urandom_range(16,0);
#10;
end
$finish;
end
initial begin
$monitor("Time=%0t | a=%0d | out=%b",$time,a,out);
$dumpfile("function_prime.vcd");
$dumpvars(0,tb_function_prime);
end
endmodule

Assignments/Task&Functions/function_prime.vcd
$date
	Fri Feb 20 12:19:54 2026
$end
$version
	Icarus Verilog
$end
$timescale
	1s
$end
$scope module tb_function_prime $end
$var wire 1 ! out $end
$var parameter 32 " N $end
$var reg 8 # a [7:0] $end
$var integer 32 $ i [31:0] $end
$scope module uut $end
$var wire 8 % a [7:0] $end
$var wire 1 ! out $end
$var parameter 32 & N $end
$scope function prime $end
$var reg 8 ' n [7:0] $end
$var integer 32 ( i [31:0] $end
$upscope $end
$upscope $end
$upscope $end
$enddefinitions $end
$comment Show the parameter values. $end
$dumpall
b1000 &
b1000 "
$end
#0
$dumpvars
b1001 (
b1001 '
b1001 %
b0 $
b1001 #
0!
$end
#10
b100 (
b100 '
b100 #
b100 %
b1 $
#20
b0 '
b0 #
b0 %
b10 $
#30
1!
b11 (
b11 '
b11 #
b11 %
b11 $
#40
0!
b1000 (
b1000 '
b1000 #
b1000 %
b100 $
#50
1!
b1101 (
b1101 '
b1101 #
b1101 %
b101 $
#60
b11 (
b11 '
b11 #
b11 %
b110 $
#70
0!
b0 '
b0 #
b0 %
b111 $
#80
b1000 (
b1000 '
b1000 #
b1000 %
b1000 $
#90
b1001 $
#100
b1100 (
b1100 '
b1100 #
b1100 %
b1010 $
#110
b1010 (
b1010 '
b1010 #
b1010 %
b1011 $
#120
b1100 $
