Assignments/Task&Functions/q21_function_sum_8bits.v
module function_sum(
input [7:0]a,b,
output [8:0]sum);
function [7:0]adder;
input [7:0]x,y;
begin
adder=x+y;
end
endfunction
assign sum=adder(a,b);
endmodule

Assignments/Task&Functions/tb_q21.v
module tb_q21;
reg [7:0]a,b;
wire [8:0]sum;
function_sum uut(.a(a), .b(b), .sum(sum));
integer i,j;
initial begin
for(i=0;i<4;i=i+1)
begin
for(j=0;j<4;j=j+1)begin
a=i; 
b=j;
#10;
end
end
end
initial begin
$monitor("Time=%0t | a=%b | b=%b | sum=%b",$time,a,b,sum);
$dumpfile("q21_function_sum.vcd");
$dumpvars(0,tb_q21);
end
endmodule

Assignments/Task&Functions/q21_function_sum.vcd
$date
	Thu Feb 19 10:20:21 2026
$end
$version
	Icarus Verilog
$end
$timescale
	1s
$end
$scope module tb_q21 $end
$var wire 9 ! sum [8:0] $end
$var reg 8 " a [7:0] $end
$var reg 8 # b [7:0] $end
$var integer 32 $ i [31:0] $end
$var integer 32 % j [31:0] $end
$scope module uut $end
$var wire 8 & a [7:0] $end
$var wire 8 ' b [7:0] $end
$var wire 9 ( sum [8:0] $end
$scope function adder $end
$var reg 8 ) x [7:0] $end
$var reg 8 * y [7:0] $end
$upscope $end
$upscope $end
$upscope $end
$enddefinitions $end
$comment Show the parameter values. $end
$dumpall
$end
#0
$dumpvars
b0 *
b0 )
b0 (
b0 '
b0 &
b0 %
b0 $
b0 #
b0 "
b0 !
$end
#10
b1 !
b1 (
b1 *
b1 #
b1 '
b1 %
#20
b10 !
b10 (
b10 *
b10 #
b10 '
b10 %
#30
b11 !
b11 (
b11 *
b11 #
b11 '
b11 %
#40
b1 !
b1 (
b0 *
b1 )
b0 #
b0 '
b1 "
b1 &
b1 $
b0 %
#50
b10 !
b10 (
b1 *
b1 #
b1 '
b1 %
#60
b11 !
b11 (
b10 *
b10 #
b10 '
b10 %
#70
b100 !
b100 (
b11 *
b11 #
b11 '
b11 %
#80
b10 !
b10 (
b0 *
b10 )
b0 #
b0 '
b10 "
b10 &
b10 $
b0 %
#90
b11 !
b11 (
b1 *
b1 #
b1 '
b1 %
#100
b100 !
b100 (
b10 *
b10 #
b10 '
b10 %
#110
b101 !
b101 (
b11 *
b11 #
b11 '
b11 %
#120
b11 !
b11 (
b0 *
b11 )
b0 #
b0 '
b11 "
b11 &
b11 $
b0 %
#130
b100 !
b100 (
b1 *
b1 #
b1 '
b1 %
#140
b101 !
b101 (
b10 *
b10 #
b10 '
b10 %
#150
b110 !
b110 (
b11 *
b11 #
b11 '
b11 %
#160
b100 $
b100 %
