3_Sequential/FSM/Sequence_detector/Mealy_FSM/1010_FSM/1010_nonoverlapping.v
module mealy_fsm(
input clk,rst,a,
output reg q);
parameter [1:0] s0=2'b00,
            s1=2'b01,
            s2=2'b10,
            s3=2'b11;
reg [1:0]state,next_state;
always@(posedge clk or posedge rst)begin
state<=2'b00; 
q<=1'b0;
if(rst)
state<=2'b00;
else
state<=next_state;
end
always@(*) begin
case(state)
s0:begin	
if(a)
next_state<=s1;
else
next_state<=s0;
end
s1:begin
if(a)
next_state<=s1;
else
next_state<=s2;
end
s2:begin
if(a)
next_state<=s3;
else	
next_state<=s0;
end
s3:begin
if(a)
next_state<=s1;
else begin
next_state<=s0;
q<=1'b1;
end
end
endcase
end
endmodule

3_Sequential/FSM/Sequence_detector/Mealy_FSM/1010_FSM/tb_1010_overlapping.v
module tb_mealy_fsm;
reg clk,rst,a;
wire q;
mealy_fsm uut(.clk(clk), .rst(rst), .a(a), .q(q));
always #5 clk=~clk;
initial begin
	clk=0; rst=1; a=0;
	#5 rst=0;
	#10 a=1;
	#10 a=1;
	#10 a=0;
	#10 a=1;
	#10 a=0;
	#10 a=1;
	#10 a=0;
	#10 a=1;
        #10 a=1;
	#10 $finish;
end
initial begin
	$monitor("Time=0%t | clk=%b | rst=%b | a=%b | q=%b",$time,clk,rst,a,q);
	$dumpfile("over_mealy_fsm");
	$dumpvars(0,tb_mealy_fsm);
end
endmodule

3_Sequential/FSM/Sequence_detector/Mealy_FSM/1010_FSM/nonover_mealy_fsm.vcd
$date
	Wed Feb 18 17:18:24 2026
$end
$version
	Icarus Verilog
$end
$timescale
	1s
$end
$scope module tb_mealy_fsm $end
$var wire 1 ! q $end
$var reg 1 " a $end
$var reg 1 # clk $end
$var reg 1 $ rst $end
$scope module uut $end
$var wire 1 " a $end
$var wire 1 # clk $end
$var wire 1 $ rst $end
$var parameter 2 % s0 $end
$var parameter 2 & s1 $end
$var parameter 2 ' s2 $end
$var parameter 2 ( s3 $end
$var reg 2 ) next_state [1:0] $end
$var reg 1 ! q $end
$var reg 2 * state [1:0] $end
$upscope $end
$upscope $end
$enddefinitions $end
$comment Show the parameter values. $end
$dumpall
b11 (
b10 '
b1 &
b0 %
$end
#0
$dumpvars
b0 *
b0 )
1$
0#
0"
0!
$end
#5
0$
1#
#10
0#
#15
b1 )
1#
1"
#20
0#
#25
b1 *
1#
#30
0#
#35
b1 *
b10 )
1#
0"
#40
0#
#45
b10 *
b11 )
1#
1"
#50
0#
#55
1!
b11 *
b0 )
1#
0"
#60
0#
#65
0!
b0 *
b1 )
1#
1"
#70
0#
#75
b1 *
b10 )
1#
0"
#80
0#
#85
b10 *
b11 )
1#
1"
#90
0#
#95
b1 )
b11 *
1#
#100
0#
#105
b1 *
1#
