Clk_Divider/Clk_divider_by_4/clk_divider_by_4_75%.v
module clk_divider_by_4(
input clk,rst,
output reg f_by_4);
reg [1:0] count;
always@(posedge clk or posedge rst) begin
if(rst) begin
f_by_4<=1'b0;
count<=2'b00;
end
else begin
  count<=count+1;
  if(count==2'b00)
       f_by_4<=~f_by_4;
  
  else if(count==2'b11)begin 
      f_by_4<=~f_by_4;
      count<=1'b0;
      end
end
end
endmodule

Clk_Divider/Clk_Divider_by_4/tb_clk_divider_by_4_62.5%.v
module tb_clk_divider_by_4;
reg clk,rst;
wire f_by_4;
clk_divider_by_4 uut(.clk(clk), .rst(rst), .f_by_4(f_by_4));
always #5 clk=~clk;
initial begin
clk=0; rst=1;
#5 rst=0;
#100 $finish;
end
initial begin
$monitor("Time=%0t | clk=%b | rst=%b | f_by_4=%b",$time,clk,rst,f_by_4);
$dumpfile("clk_divider_by_4_62.5%.vcd");
$dumpvars(0,tb_clk_divider_by_4);
end
endmodule

Clk_Divider/Clk_Divider_by_4/clk_divider_by_4_75%.vcd
$date
	Mon Mar  2 17:04:04 2026
$end
$version
	Icarus Verilog
$end
$timescale
	1s
$end
$scope module tb_clk_divider_by_4 $end
$var wire 1 ! f_by_4 $end
$var reg 1 " clk $end
$var reg 1 # rst $end
$scope module uut $end
$var wire 1 " clk $end
$var wire 1 # rst $end
$var reg 2 $ count [1:0] $end
$var reg 1 ! f_by_4 $end
$upscope $end
$upscope $end
$enddefinitions $end
$comment Show the parameter values. $end
$dumpall
$end
#0
$dumpvars
b0 $
1#
0"
0!
$end
#5
1!
b1 $
0#
1"
#10
0"
#15
b10 $
1"
#20
0"
#25
b11 $
1"
#30
0"
#35
0!
b0 $
1"
#40
0"
#45
1!
b1 $
1"
#50
0"
#55
b10 $
1"
#60
0"
#65
b11 $
1"
#70
0"
#75
0!
b0 $
1"
#80
0"
#85
1!
b1 $
1"
#90
0"
#95
b10 $
1"
#100
0"
#105
b11 $
1"
