Clk_Divider/Clk_Divider_by_4/clk_divider_by_4_62.5%.v
module clk_divider_by_4(
input clk,rst,
output f_by_4);
reg [1:0] count;
reg r_pos;
reg r_neg;
always@(posedge clk or posedge rst) begin
	if(rst)
		count<=2'b00;
	else
		count<=count+1;
end

always@(posedge clk or posedge rst) begin
	if(rst)
		r_pos<=1'b0;
	else
		r_pos<=(count==2'b00 || count==2'b01);
end

always@(negedge clk or posedge rst) begin
	if(rst)
		r_neg<=1'b0;
	else
		r_neg<=r_pos;
end

assign f_by_4= r_pos | r_neg;
endmodule

Clk_Divider/Clk_Divider_by_4/tb_clk_divider_by_4_62.5%.v
module tb_clk_divider_by_4;
reg clk,rst;
wire f_by_4;
clk_divider_by_4 uut(.clk(clk), .rst(rst), .f_by_4(f_by_4));
always #5 clk=~clk;
initial begin
clk=0; rst=1;
#5 rst=0;
#100 $finish;
end
initial begin
$monitor("Time=%0t | clk=%b | rst=%b | f_by_4=%b",$time,clk,rst,f_by_4);
$dumpfile("clk_divider_by_4_62.5%.vcd");
$dumpvars(0,tb_clk_divider_by_4);
end
endmodule

Clk_Divider/Clk_Divider_by_4/clk_divider_by_4_62.5%.vcd
$date
	Tue Mar  3 10:09:19 2026
$end
$version
	Icarus Verilog
$end
$timescale
	1s
$end
$scope module tb_clk_divider_by_4 $end
$var wire 1 ! f_by_4 $end
$var reg 1 " clk $end
$var reg 1 # rst $end
$scope module uut $end
$var wire 1 " clk $end
$var wire 1 ! f_by_4 $end
$var wire 1 # rst $end
$var reg 2 $ count [1:0] $end
$var reg 1 % r_neg $end
$var reg 1 & r_pos $end
$upscope $end
$upscope $end
$enddefinitions $end
$comment Show the parameter values. $end
$dumpall
$end
#0
$dumpvars
0&
0%
b0 $
1#
0"
0!
$end
#5
1!
1&
b1 $
0#
1"
#10
1%
0"
#15
b10 $
1"
#20
0"
#25
0&
b11 $
1"
#30
0!
0%
0"
#35
b0 $
1"
#40
0"
#45
1!
1&
b1 $
1"
#50
1%
0"
#55
b10 $
1"
#60
0"
#65
0&
b11 $
1"
#70
0!
0%
0"
#75
b0 $
1"
#80
0"
#85
1!
1&
b1 $
1"
#90
1%
0"
#95
b10 $
1"
#100
0"
#105
0&
b11 $
1"
