3_Sequential/Shift_Registers/Bidirectional_Shift_Registers/bidirectional_shifter.v
module bidirectional_shifter(
input clk,rst,mode,
input in,
output reg out);
reg [3:0]q;
always@(posedge clk or posedge rst)begin
if(rst)
q<=4'b0000;
else if (mode)begin
q<=({in,q[3:1]});
out<=q[0];
end
else begin
q<=({q[2:0],in});
out<=q[3];
end
end
endmodule

3_Sequential/Shift_Registers/Bidirectional_Shift_Registers/tb_bidirectional_shifter.v
module tb_bidirectional_shifter;
reg clk,rst,mode;
reg in;
wire out;
bidirectional_shifter uut(.clk(clk), .rst(rst), .mode(mode),  .in(in), .out(out));
always #5 clk=~clk;
initial begin
clk=0; rst=1; in=1; mode=1;
#5 rst=1; 
#10 rst=0; in=1; mode=1;
#10 in=0;
#10 in=1;
#10 in=0;
#30 rst=1;
#5 rst=0; mode=0;
#5 in=1;
#10 in=0;
#30 $finish;
end
initial begin
$monitor("Time=%0t | clk=%b | rst =%b | mode=%b |  in=%b | out=%b",$time,clk,rst,mode,in,out);
$dumpfile("bidirectional_shifter.vcd");
$dumpvars(0,tb_bidirectional_shifter);
end
endmodule

3_Sequential/Shift_Registers/Bidirectional_Shift_Registers/bidirectional_shifter.vcd
$date
	Mon Feb 16 21:42:05 2026
$end
$version
	Icarus Verilog
$end
$timescale
	1s
$end
$scope module tb_bidirectional_shifter $end
$var wire 1 ! out $end
$var reg 1 " clk $end
$var reg 1 # in $end
$var reg 1 $ mode $end
$var reg 1 % rst $end
$scope module uut $end
$var wire 1 " clk $end
$var wire 1 # in $end
$var wire 1 $ mode $end
$var wire 1 % rst $end
$var reg 1 ! out $end
$var reg 4 & q [3:0] $end
$upscope $end
$upscope $end
$enddefinitions $end
$comment Show the parameter values. $end
$dumpall
$end
#0
$dumpvars
b0 &
1%
1$
1#
0"
x!
$end
#5
1"
#10
0"
#15
0!
b1000 &
1"
0%
#20
0"
#25
b100 &
1"
0#
#30
0"
#35
b1010 &
1"
1#
#40
0"
#45
b101 &
1"
0#
#50
0"
#55
1!
b10 &
1"
#60
0"
#65
0!
b1 &
1"
#70
0"
#75
b0 &
1"
1%
#80
0"
0$
0%
#85
b1 &
1"
1#
#90
0"
#95
b10 &
1"
0#
#100
0"
#105
b100 &
1"
#110
0"
#115
b1000 &
1"
#120
0"
#125
1!
b0 &
1"
